business_metrics.py
zakayz_business_metrics-0.1.0.dist-info/METADATA
zakayz_business_metrics-0.1.0.dist-info/WHEEL
zakayz_business_metrics-0.1.0.dist-info/entry_points.txt
zakayz_business_metrics-0.1.0.dist-info/top_level.txt
zakayz_business_metrics-0.1.0.dist-info/RECORD
