Metadata-Version: 2.1
Name: zakayz_business_metrics
Version: 0.1.0
Summary: считает roi
